hologger/__init__.py
hologger/apps.py
hologger/handlers.py
hologger/middleware.py
hologger/models.py
hologger/router.py
hologger/serializers.py
hologger/settings.py
hologger/signal.py
hologger/urls.py
hologger/wsgi.py
hologger-0.0.7.dist-info/METADATA
hologger-0.0.7.dist-info/WHEEL
hologger-0.0.7.dist-info/top_level.txt
hologger-0.0.7.dist-info/RECORD
