Metadata-Version: 2.1
Name: hologger
Version: 0.0.7
Summary: Write log at db
Home-page: UNKNOWN
Author: Checkill Kim
Author-email: cortmzzang@gmail.com
License: MIT
Platform: UNKNOWN
